{
  "name": "牵线木偶",
  "form": "",
  "regionalFormName": "",
  "initialStageName": "",
  "hasAltColor": "",
  "stage": "Ⅰ阶",
  "type": "",
  "description": "总是一副亲切愉悦的样子，备受小洛克们的喜欢，但似乎在没人的时候它们不会展现出一丁点生气。曾经不分昼夜持续观测一年，且让样本知道自己被观测，期间样本呈现愉悦的状态。停止观测一小时后样本所有生命体征均消失。",
  "element": "幻",
  "element2": "",
  "ability": "",
  "abilityDesc": "",
  "hp": 100,
  "physicalAttack": 86,
  "magicAttack": 90,
  "physicalDefense": 72,
  "magicDefense": 102,
  "speed": 84,
  "size": "",
  "weight": "",
  "distribution": "",
  "questTasks": [],
  "questSkillStones": [],
  "skills": [],
  "skillUnlockLevels": [],
  "bloodlineSkills": [],
  "learnableSkillStones": [],
  "evolutionCondition": "",
  "updateVersion": "",
  "skillDetails": [],
  "bloodlineSkillDetails": [],
  "learnableSkillStoneDetails": []
}